JRX/__init__.py
JRX/core.py
JRX/janus/__init__.py
JRX/janus/janusflow/__init__.py
JRX/janus/janusflow/models/__init__.py
JRX/janus/janusflow/models/clip_encoder.py
JRX/janus/janusflow/models/image_processing_vlm.py
JRX/janus/janusflow/models/modeling_vlm.py
JRX/janus/janusflow/models/processing_vlm.py
JRX/janus/janusflow/models/siglip_vit.py
JRX/janus/janusflow/models/uvit.py
JRX/janus/models/__init__.py
JRX/janus/models/clip_encoder.py
JRX/janus/models/image_processing_vlm.py
JRX/janus/models/modeling_vlm.py
JRX/janus/models/processing_vlm.py
JRX/janus/models/projector.py
JRX/janus/models/siglip_vit.py
JRX/janus/models/vq_model.py
JRX/janus/utils/__init__.py
JRX/janus/utils/conversation.py
JRX/janus/utils/io.py
jrx_ai-0.1.4.dist-info/METADATA
jrx_ai-0.1.4.dist-info/WHEEL
jrx_ai-0.1.4.dist-info/top_level.txt
jrx_ai-0.1.4.dist-info/RECORD
